celebrity_births/__init__.py
celebrity_births/date.py
celebrity_births/example.py
celebrity_births/scraper.py
celebrity_births_test-0.0.4.dist-info/LICENSE
celebrity_births_test-0.0.4.dist-info/METADATA
celebrity_births_test-0.0.4.dist-info/WHEEL
celebrity_births_test-0.0.4.dist-info/top_level.txt
celebrity_births_test-0.0.4.dist-info/RECORD
