Metadata-Version: 2.1
Name: celebrity-births-test
Version: 0.0.4
Summary: Mock package that allows you to find celebrity by date of birth
Home-page: https://github.com/IvanYingX/project_structure_pypi.git
Author: Ivan Ying
License: MIT
Platform: UNKNOWN
Requires-Dist: requests
Requires-Dist: beautifulsoup4
